{"appId":"BPM","workflow":{"activities":[{"id":"1496817111894","type":"startEvent","name":"开始","description":""},{"id":"1496817111895","type":"userTask","name":"自动化流程图","description":"编辑客户描述","canSkip":false,"taskType":"anyone","assignee":{"ext_bpm":["instance##owner$$流程发起人"]},"bpmExtension":{"actionCode":"","executionType":"update","executionName":"编辑对象","entityId":"AccountObj","entityName":"客户","objectId":{"expression":"activity_0##AccountObj"}}},{"id":"1496817111898","name":"结束","description":"","type":"endEvent"}],"variables":[{"id":"activity_0##AccountObj","type":{"name":"text"}},{"id":"activity_1496817111895##AccountObj","type":{"name":"text"}}],"transitions":[{"id":"1496817111897","fromId":"1496817111894","toId":"1496817111895"},{"id":"1496817111899","fromId":"1496817111895","toId":"1496817111898"}]},"extension":{"diagram":[{"id":"1496817111896","attr":{"width":220,"height":540,"x":40,"y":60}},{"id":"1496817111894","attr":{"width":60,"height":60,"x":120,"y":125}},{"id":"1496817111895","attr":{"width":160,"height":50,"x":70,"y":260}},{"id":"1496817111898","attr":{"width":60,"height":60,"x":122,"y":400}},{"id":"1496817111899","attr":{"d":"M150,310 v45 a1,1 0 0 0 1,1 h0 a1,1 0 0 1 1,1 v45","toPosition":"top","fromPosition":"bottom","type":"polyline"}},{"id":"1496817111897","attr":{"d":"M150,185 v38 a0,0 0 0 0 0,0 h0 a0,0 0 0 1 0,0 v38","toPosition":"top","fromPosition":"bottom","type":"polyline"}}],"pools":[{"lanes":[{"id":"1496817111896","name":"阶段","description":"","activities":["1496817111894","1496817111895","1496817111898"]}]}],"svg":"<svg xmlns=\"http://www.w3.org/2000/svg\" class=\"paas-bpm-canvas\" height=650 width=310 tabindex=\"0\" style=\"-webkit-tap-highlight-color: rgba(0, 0, 0, 0);\"><defs><marker id=\"end-arrow\" markerHeight=\"10\" markerWidth=\"10\" markerUnits=\"userSpaceOnUse\" orient=\"auto\" refX=\"5\" refY=\"0\" viewBox=\"-5 -5 10 10\"><path d=\"M 0,0 m -5,-5 L 5,0 L -5,5 Z\" fill=\"#666666\"></path></marker><marker id=\"end-arrow-colored\" markerHeight=\"10\" markerWidth=\"10\" markerUnits=\"userSpaceOnUse\" orient=\"auto\" refX=\"5\" refY=\"0\" viewBox=\"-5 -5 10 10\"><path d=\"M 0,0 m -5,-5 L 5,0 L -5,5 Z\" fill=\"#49bffc\"></path></marker><marker id=\"approval-yes\" markerHeight=\"10\" markerWidth=\"10\" markerUnits=\"userSpaceOnUse\" orient=\"auto\" refX=\"-10\" refY=\"5\"><g><circle fill=\"#7FC25D\" cx=\"5\" cy=\"5\" r=\"5\"></circle></g></marker><marker id=\"approval-no\" markerHeight=\"10\" markerWidth=\"10\" markerUnits=\"userSpaceOnUse\" orient=\"auto\" refX=\"-10\" refY=\"5\"><g><circle fill=\"#DC9688\" cx=\"5\" cy=\"5\" r=\"5\"></circle></g></marker><filter id=\"box-shadow\"><feGaussianBlur in=\"SourceAlpha\" stdDeviation=\"2\"></feGaussianBlur><feOffset dx=\"0\" dy=\"1\" result=\"offsetblur\"></feOffset><feFlood flood-color=\"black\" flood-opacity=\"0.06\"></feFlood><feComposite in2=\"offsetblur\" operator=\"in\"></feComposite><feMerge><feMergeNode></feMergeNode><feMergeNode in=\"SourceGraphic\"></feMergeNode></feMerge></filter><style type=\"text/css\">svg {\n        background-color: #f3f3f5;\n      }\n\n      g[type=pool] {\n        font-size: 13px;\n      }</style></defs><g class=\"paas-bpm-canvas-wrapper\" height=\"100%\" width=\"100%\" transform=\"translate(0,0) scale(1)\"><g data-id=\"1496817111896\" shape=\"rectangle\" type=\"pool\" x=\"40\" y=\"60\" width=\"220\" height=\"540\" transform=\"translate(40,60)\" tabindex=\"0\" class=\"paas-bpm-resizable\" style=\"-webkit-tap-highlight-color: rgba(0, 0, 0, 0);\"><rect fill=\"transparent\" width=\"220\" height=\"540\" namePos=\"top\" highlight=\"false\" stroke=\"#cccccc\" rx=\"0\" ry=\"0\" resizable=\"true\" placeAt=\"first\" external=\"<rect fill=&quot;transparent&quot; width=&quot;220&quot; height=&quot;60&quot; stroke=&quot;transparent&quot; rx=&quot;0&quot; ry=&quot;0&quot; y=&quot;0&quot; class=&quot;paas-bpm-pool-drag-area&quot;></rect>\" type=\"rect\"></rect><g fill=\"transparent\" name=\"bpm-shape-focus-node\" class=\"hide\"><rect width=\"220\" height=\"540\" rx=\"0\" ry=\"0\" fill=\"transparent\"></rect><rect width=\"9\" height=\"9\" name=\"left\" fill=\"white\" class=\"paas-bpm-inner-connect-point paas-bpm-connect-point resize\" rx=\"0\" ry=\"0\" x=\"-4.5\" y=\"265.5\"></rect><rect width=\"9\" height=\"9\" name=\"top\" fill=\"white\" class=\"paas-bpm-inner-connect-point paas-bpm-connect-point resize\" rx=\"0\" ry=\"0\" x=\"105.5\" y=\"-4.5\"></rect><rect width=\"9\" height=\"9\" name=\"right\" fill=\"white\" class=\"paas-bpm-inner-connect-point ew-resize paas-bpm-connect-point\" rx=\"0\" ry=\"0\" x=\"215.5\" y=\"265.5\" style=\"-webkit-tap-highlight-color: rgba(0, 0, 0, 0);\"></rect><rect width=\"9\" height=\"9\" name=\"bottom\" fill=\"white\" class=\"paas-bpm-inner-connect-point ns-resize paas-bpm-connect-point\" rx=\"0\" ry=\"0\" x=\"105.5\" y=\"535.5\" style=\"-webkit-tap-highlight-color: rgba(0, 0, 0, 0);\"></rect></g><g name=\"external\"><rect fill=\"transparent\" width=\"220\" height=\"60\" stroke=\"transparent\" rx=\"0\" ry=\"0\" y=\"0\" class=\"paas-bpm-pool-drag-area\"></rect></g><text text-anchor=\"middle\" name=\"name\" y=\"30\" x=\"110\">阶段</text><g name=\"error-node\" class=\"hide\" transform=\"translate(0, 545)\"><text text-anchor=\"middle\" alignment-baseline=\"middle\" fill=\"#f57a62\" x=\"0\" y=\"15\"></text></g><rect width=\"18\" height=\"18\" class=\"paas-bpm-badge\" x=\"0.5\" y=\"0.5\" fill=\"#ccc\"></rect><text class=\"paas-bpm-badge-text\" text-anchor=\"middle\" fill=\"#70757f\" x=\"9\" y=\"13\">1</text></g><g name=\"line-wrapper\"><g fill=\"transparent\" tabindex=\"0\" data-id=\"1496817111899\"><path type=\"polyline\" d=\"M150,310 v45 a1,1 0 0 0 1,1 h0 a1,1 0 0 1 1,1 v45\" from-position=\"bottom\" stroke-width=\"1\" stroke=\"#aaaaaa\" marker-end=\"url(#end-arrow)\" to-position=\"top\" start-id=\"1496817111895\" end-id=\"1496817111898\"></path></g><g tabindex=\"0\" data-id=\"1496817111897\"><path d=\"M150,185 v38 a0,0 0 0 0 0,0 h0 a0,0 0 0 1 0,0 v38\" start-id=\"1496817111894\" end-id=\"1496817111895\" fill=\"transparent\" stroke-width=\"1\" type=\"polyline\" to-position=\"top\" from-position=\"bottom\" stroke=\"#aaaaaa\" marker-end=\"url(#end-arrow)\"></path></g></g><g data-id=\"1496817111894\" shape=\"rectangle\" type=\"startEvent\" x=\"120\" y=\"125\" width=\"60\" height=\"60\" transform=\"translate(120,125)\" tabindex=\"0\" style=\"-webkit-tap-highlight-color: rgba(0, 0, 0, 0);\" class=\"\"><rect fill=\"#f3f3f5\" rx=\"60\" ry=\"60\" width=\"60\" height=\"60\" stroke=\"#70757f\" stroke-width=\"3\" color=\"#70757f\" type=\"rect\"></rect><g fill=\"transparent\" name=\"bpm-shape-focus-node\" class=\"hide\" stroke=\"\"><rect width=\"60\" height=\"60\" rx=\"0\" ry=\"0\" fill=\"transparent\"></rect><rect width=\"9\" height=\"9\" name=\"left\" fill=\"white\" class=\"paas-bpm-inner-connect-point paas-bpm-connect-point resize\" rx=\"9\" ry=\"9\" x=\"-4.5\" y=\"25.5\"></rect><rect width=\"15\" height=\"15\" name=\"left\" fill=\"transparent\" stroke=\"transparent\" class=\"paas-bpm-outer-connect-point\" rx=\"15\" ry=\"15\" x=\"-7.5\" y=\"22.5\" style=\"-webkit-tap-highlight-color: rgba(0, 0, 0, 0);\"></rect><rect width=\"9\" height=\"9\" name=\"top\" fill=\"white\" class=\"paas-bpm-inner-connect-point paas-bpm-connect-point resize\" rx=\"9\" ry=\"9\" x=\"25.5\" y=\"-4.5\"></rect><rect width=\"15\" height=\"15\" name=\"top\" fill=\"transparent\" stroke=\"transparent\" class=\"paas-bpm-outer-connect-point\" rx=\"15\" ry=\"15\" x=\"22.5\" y=\"-7.5\" style=\"-webkit-tap-highlight-color: rgba(0, 0, 0, 0);\"></rect><rect width=\"9\" height=\"9\" name=\"right\" fill=\"white\" class=\"paas-bpm-inner-connect-point ew-resize paas-bpm-connect-point\" rx=\"9\" ry=\"9\" x=\"55.5\" y=\"25.5\"></rect><rect width=\"15\" height=\"15\" name=\"right\" fill=\"transparent\" stroke=\"transparent\" class=\"paas-bpm-outer-connect-point\" rx=\"15\" ry=\"15\" x=\"52.5\" y=\"22.5\" style=\"-webkit-tap-highlight-color: rgba(0, 0, 0, 0);\"></rect><rect width=\"9\" height=\"9\" name=\"bottom\" fill=\"white\" class=\"paas-bpm-inner-connect-point ns-resize paas-bpm-connect-point\" rx=\"9\" ry=\"9\" x=\"25.5\" y=\"55.5\"></rect><rect width=\"15\" height=\"15\" name=\"bottom\" fill=\"transparent\" stroke=\"transparent\" class=\"paas-bpm-outer-connect-point\" rx=\"15\" ry=\"15\" x=\"22.5\" y=\"52.5\" style=\"-webkit-tap-highlight-color: rgba(0, 0, 0, 0);\"></rect></g><text text-anchor=\"middle\" name=\"name\" y=\"35\" x=\"30\" fill=\"#70757f\">开始</text><g name=\"error-node\" class=\"hide\" transform=\"translate(0, 65)\"><text text-anchor=\"middle\" alignment-baseline=\"middle\" fill=\"#f57a62\" x=\"0\" y=\"15\"></text></g></g><g data-id=\"1496817111895\" shape=\"rectangle\" type=\"userTask\" x=\"70\" y=\"260\" width=\"160\" height=\"50\" transform=\"translate(70,260)\" tabindex=\"0\" style=\"-webkit-tap-highlight-color: rgba(0, 0, 0, 0);\" class=\"bpm-shape-focus-node bpm-draw-polyline-able node-focused\" status=\"normal\"><rect fill=\"white\" width=\"160\" height=\"50\" rx=\"3\" ry=\"3\" filter=\"url(#box-shadow)\" type=\"rect\"></rect><g fill=\"transparent\" name=\"bpm-shape-focus-node\" class=\"hide\" stroke=\"#49bffc\"><rect width=\"160\" height=\"50\" rx=\"0\" ry=\"0\" fill=\"transparent\"></rect><rect width=\"9\" height=\"9\" name=\"left\" fill=\"white\" class=\"paas-bpm-inner-connect-point paas-bpm-connect-point resize\" rx=\"9\" ry=\"9\" x=\"-4.5\" y=\"20.5\"></rect><rect width=\"15\" height=\"15\" name=\"left\" fill=\"transparent\" stroke=\"transparent\" class=\"paas-bpm-outer-connect-point\" rx=\"15\" ry=\"15\" x=\"-7.5\" y=\"17.5\" style=\"-webkit-tap-highlight-color: rgba(0, 0, 0, 0);\"></rect><rect width=\"9\" height=\"9\" name=\"top\" fill=\"white\" class=\"paas-bpm-inner-connect-point paas-bpm-connect-point resize\" rx=\"9\" ry=\"9\" x=\"75.5\" y=\"-4.5\"></rect><rect width=\"15\" height=\"15\" name=\"top\" fill=\"transparent\" stroke=\"transparent\" class=\"paas-bpm-outer-connect-point\" rx=\"15\" ry=\"15\" x=\"72.5\" y=\"-7.5\" style=\"-webkit-tap-highlight-color: rgba(0, 0, 0, 0);\"></rect><rect width=\"9\" height=\"9\" name=\"right\" fill=\"white\" class=\"paas-bpm-inner-connect-point ew-resize paas-bpm-connect-point\" rx=\"9\" ry=\"9\" x=\"155.5\" y=\"20.5\"></rect><rect width=\"15\" height=\"15\" name=\"right\" fill=\"transparent\" stroke=\"transparent\" class=\"paas-bpm-outer-connect-point\" rx=\"15\" ry=\"15\" x=\"152.5\" y=\"17.5\" style=\"-webkit-tap-highlight-color: rgba(0, 0, 0, 0);\"></rect><rect width=\"9\" height=\"9\" name=\"bottom\" fill=\"white\" class=\"paas-bpm-inner-connect-point ns-resize paas-bpm-connect-point\" rx=\"9\" ry=\"9\" x=\"75.5\" y=\"45.5\"></rect><rect width=\"15\" height=\"15\" name=\"bottom\" fill=\"transparent\" stroke=\"transparent\" class=\"paas-bpm-outer-connect-point\" rx=\"15\" ry=\"15\" x=\"72.5\" y=\"42.5\" style=\"-webkit-tap-highlight-color: rgba(0, 0, 0, 0);\"></rect></g><text text-anchor=\"middle\" name=\"name\" y=\"30\" x=\"80\">编辑客户</text><g name=\"error-node\" class=\"hide\" transform=\"translate(80, 55)\"><text text-anchor=\"middle\" alignment-baseline=\"middle\" fill=\"#f57a62\" x=\"0\" y=\"15\"><tspan font-size=\"20\"></tspan><tspan dy=\"-5\">该节点配置错误</tspan></text></g></g><g data-id=\"1496817111898\" shape=\"rectangle\" type=\"endEvent\" x=\"122\" y=\"400\" width=\"60\" height=\"60\" transform=\"translate(122,400)\" tabindex=\"0\" status=\"normal\" style=\"-webkit-tap-highlight-color: rgba(0, 0, 0, 0);\" class=\"\"><rect fill=\"#f3f3f5\" rx=\"60\" ry=\"60\" width=\"60\" height=\"60\" stroke=\"#70757f\" stroke-width=\"3\" color=\"#70757f\" external=\"<rect x=&quot;4&quot; y=&quot;4&quot; fill=&quot;transparent&quot; rx=&quot;52&quot; ry=&quot;52&quot; width=&quot;52&quot; height=&quot;52&quot; stroke=&quot;#70757f&quot; stroke-width=&quot;1&quot; color=&quot;#e67373&quot; type=&quot;rect&quot;></rect>\" type=\"rect\"></rect><g fill=\"transparent\" name=\"bpm-shape-focus-node\" class=\"hide\" stroke=\"\"><rect width=\"60\" height=\"60\" rx=\"0\" ry=\"0\" fill=\"transparent\"></rect><rect width=\"9\" height=\"9\" name=\"left\" fill=\"white\" class=\"paas-bpm-inner-connect-point paas-bpm-connect-point resize\" rx=\"9\" ry=\"9\" x=\"-4.5\" y=\"25.5\"></rect><rect width=\"15\" height=\"15\" name=\"left\" fill=\"transparent\" stroke=\"transparent\" class=\"paas-bpm-outer-connect-point\" rx=\"15\" ry=\"15\" x=\"-7.5\" y=\"22.5\" style=\"-webkit-tap-highlight-color: rgba(0, 0, 0, 0);\"></rect><rect width=\"9\" height=\"9\" name=\"top\" fill=\"white\" class=\"paas-bpm-inner-connect-point paas-bpm-connect-point resize\" rx=\"9\" ry=\"9\" x=\"25.5\" y=\"-4.5\"></rect><rect width=\"15\" height=\"15\" name=\"top\" fill=\"transparent\" stroke=\"transparent\" class=\"paas-bpm-outer-connect-point\" rx=\"15\" ry=\"15\" x=\"22.5\" y=\"-7.5\" style=\"-webkit-tap-highlight-color: rgba(0, 0, 0, 0);\"></rect><rect width=\"9\" height=\"9\" name=\"right\" fill=\"white\" class=\"paas-bpm-inner-connect-point ew-resize paas-bpm-connect-point\" rx=\"9\" ry=\"9\" x=\"55.5\" y=\"25.5\"></rect><rect width=\"15\" height=\"15\" name=\"right\" fill=\"transparent\" stroke=\"transparent\" class=\"paas-bpm-outer-connect-point\" rx=\"15\" ry=\"15\" x=\"52.5\" y=\"22.5\" style=\"-webkit-tap-highlight-color: rgba(0, 0, 0, 0);\"></rect><rect width=\"9\" height=\"9\" name=\"bottom\" fill=\"white\" class=\"paas-bpm-inner-connect-point ns-resize paas-bpm-connect-point\" rx=\"9\" ry=\"9\" x=\"25.5\" y=\"55.5\"></rect><rect width=\"15\" height=\"15\" name=\"bottom\" fill=\"transparent\" stroke=\"transparent\" class=\"paas-bpm-outer-connect-point\" rx=\"15\" ry=\"15\" x=\"22.5\" y=\"52.5\" style=\"-webkit-tap-highlight-color: rgba(0, 0, 0, 0);\"></rect></g><g name=\"external\"><rect x=\"4\" y=\"4\" fill=\"transparent\" rx=\"52\" ry=\"52\" width=\"52\" height=\"52\" stroke=\"#70757f\" stroke-width=\"1\" color=\"#e67373\" type=\"rect\"></rect></g><text text-anchor=\"middle\" name=\"name\" y=\"35\" x=\"30\" fill=\"#70757f\">结束</text><g name=\"error-node\" class=\"hide\" transform=\"translate(30, 65)\"><text text-anchor=\"middle\" alignment-baseline=\"middle\" fill=\"#f57a62\" x=\"0\" y=\"15\"><tspan font-size=\"20\"></tspan><tspan dy=\"-5\">该节点至少有一根连入的线</tspan></text></g></g></g></svg>"},"enabled":true,"id":"","name":"编辑客户对象","description":"编辑客户对象描述","entryType":"AccountObj","entryTypeName":"客户","rangeCircleIds":[],"rangeEmployeeIds":[6251],"rangeGroupIds":[],"rangeRoleIds":[],"scope":"崔永旭"}